{
	"name": "8_Selecting_From_Folder",
	"properties": {
		"folder": {
			"name": "nyc_taxi/Discovery"
		},
		"content": {
			"query": "-- This is auto-generated code\n\n\nUSE nyc_taxi_discovery\n\nSELECT * FROM sys.external_data_sources;\n\nGO\n-- SELECTING DATA FROM FOLDER\nSELECT\n    TOP 100 *\nFROM\n    OPENROWSET(\n        BULK 'trip_data_green_csv/year=2020/month=01/green_tripdata_2020-01.csv',\n        DATA_SOURCE = 'nyc_taxi_data_raw',\n        FORMAT = 'CSV',\n        PARSER_VERSION = '2.0',\n        HEADER_ROW = TRUE\n    ) AS [result]\n\n\n-- SELECT DATA FROM FOLDER\n\nSELECT\n    TOP 100 *\nFROM\n    OPENROWSET(\n        -- You can use wildchard character as well.\n        BULK 'trip_data_green_csv/year=2020/month=01/',\n        DATA_SOURCE = 'nyc_taxi_data_raw',\n        FORMAT = 'CSV',\n        PARSER_VERSION = '2.0',\n        HEADER_ROW = TRUE\n    ) AS [result]\n\n\n\n-- SELECTING FROM SUBFOLDERS\n-- If you want to select data from subfolders recursively, you should use double **. \nSELECT\n    TOP 100 *\nFROM\n    OPENROWSET(\n        BULK 'trip_data_green_csv/year=2020/**',\n        DATA_SOURCE = 'nyc_taxi_data_raw',\n        FORMAT = 'CSV',\n        PARSER_VERSION = '2.0',\n        HEADER_ROW = TRUE\n    ) AS [result]\n\n\n-- Select only from specific Subfolders\n\nSELECT\n    TOP 100 *\nFROM\n    OPENROWSET(\n        -- Use it within ()\n        BULK \n        ( \n            'trip_data_green_csv/year=2020/month=01/*',\n            'trip_data_green_csv/year=2020/month=02/*' \n        ),\n        DATA_SOURCE = 'nyc_taxi_data_raw',\n        FORMAT = 'CSV',\n        PARSER_VERSION = '2.0',\n        HEADER_ROW = TRUE\n    ) AS [result]\n\n\n\n-- Get File Name as well\n\nSELECT\n    TOP 100 *,\n    -- use  .filename()\n    my_result.filename() as file_name\nFROM\n    OPENROWSET(\n        -- Use it within ()\n        BULK \n        ( \n            'trip_data_green_csv/year=2020/month=01/*',\n            'trip_data_green_csv/year=2020/month=02/*' \n        ),\n        DATA_SOURCE = 'nyc_taxi_data_raw',\n        FORMAT = 'CSV',\n        PARSER_VERSION = '2.0',\n        HEADER_ROW = TRUE\n    ) AS my_result\n\n\n-- How many rows in each file\n\n\nSELECT\n    my_result.filename() as file_name,\n    COUNT(1) as reacord_count\nFROM\n    OPENROWSET(\n        -- Use it within ()\n        BULK  'trip_data_green_csv/year=2020/**',\n        DATA_SOURCE = 'nyc_taxi_data_raw',\n        FORMAT = 'CSV',\n        PARSER_VERSION = '2.0',\n        HEADER_ROW = TRUE\n    ) AS my_result\nGROUP BY my_result.filename()\nORDER BY my_result.filename()\n\n\n\n\n-- FilePath (folder + Filename)\n\nSELECT\nTOP 100\n    my_result.filename() as file_name,\n    my_result.filepath() as file_path,\n    *\nFROM\n    OPENROWSET(\n        -- Use it within ()\n        BULK  'trip_data_green_csv/year=2020/**',\n        DATA_SOURCE = 'nyc_taxi_data_raw',\n        FORMAT = 'CSV',\n        PARSER_VERSION = '2.0',\n        HEADER_ROW = TRUE\n    ) AS my_result\n\n\n\n-- File Path Can also Take a Params\n\n\n\nSELECT\nTOP 100\n    my_result.filename() as file_name,\n    my_result.filepath() as filepath,\n    -- This will take year from the folderpath in BULK\n    my_result.filepath(1) as year,\n    my_result.filepath(2) as month,\n    *\nFROM\n    OPENROWSET(\n        BULK  'trip_data_green_csv/year=*/month=*/*.csv',\n        DATA_SOURCE = 'nyc_taxi_data_raw',\n        FORMAT = 'CSV',\n        PARSER_VERSION = '2.0',\n        HEADER_ROW = TRUE\n    ) AS my_result\n\n\n\n-- FIltering File Name\n-- By this way we can select the files we want based on year month and etc.\n\nSELECT\n    my_result.filename() as file_name,\n    my_result.filepath() as filepath,\n    my_result.filepath(1) as year,\n    my_result.filepath(2) as month,\n    COUNT(1) as record_count\nFROM\n    OPENROWSET(\n        BULK  'trip_data_green_csv/year=*/month=*/*.csv',\n        DATA_SOURCE = 'nyc_taxi_data_raw',\n        FORMAT = 'CSV',\n        PARSER_VERSION = '2.0',\n        HEADER_ROW = TRUE\n    ) AS my_result\nWHERE \n    my_result.filepath(1) = '2020'\n    AND my_result.filepath(2) in ('06', '07', '08')\nGROUP BY my_result.filename(), my_result.filepath(1), my_result.filepath(2)\nORDER BY my_result.filename(), my_result.filepath(1), my_result.filepath(2)\n\n\n\nSELECT\n    my_result.filename() as file_name,\n    my_result.filepath(1) as year,\n    my_result.filepath(2) as month,\n    COUNT(1) as record_count\nFROM\n    OPENROWSET(\n        BULK  'trip_data_green_csv/year=*/month=*/*.csv',\n        DATA_SOURCE = 'nyc_taxi_data_raw',\n        FORMAT = 'CSV',\n        PARSER_VERSION = '2.0',\n        HEADER_ROW = TRUE\n    ) AS my_result\nWHERE \n    my_result.filepath(1) = '2020'\n    AND my_result.filepath(2) in ('06', '07', '08')\nGROUP BY my_result.filename(), my_result.filepath(1), my_result.filepath(2)\nORDER BY my_result.filename(), my_result.filepath(1), my_result.filepath(2)\n",
			"metadata": {
				"language": "sql"
			},
			"currentConnection": {
				"databaseName": "nyc_taxi_discovery",
				"poolName": "Built-in"
			},
			"resultLimit": 5000
		},
		"type": "SqlQuery"
	}
}